cosmicexcuse/__init__.py
cosmicexcuse/__version__.py
cosmicexcuse/analyzer.py
cosmicexcuse/cli.py
cosmicexcuse/exceptions.py
cosmicexcuse/formatter.py
cosmicexcuse/generator.py
cosmicexcuse/leaderboard.py
cosmicexcuse/markov.py
cosmicexcuse/utils.py
cosmicexcuse/data/__init__.py
cosmicexcuse/data/loader.py
cosmicexcuse/data/bn/ai.json
cosmicexcuse/data/bn/blame.json
cosmicexcuse/data/bn/connectors.json
cosmicexcuse/data/bn/cosmic.json
cosmicexcuse/data/bn/intensifiers.json
cosmicexcuse/data/bn/quantum.json
cosmicexcuse/data/bn/recommendations.json
cosmicexcuse/data/bn/technical.json
cosmicexcuse/data/en/ai.json
cosmicexcuse/data/en/blame.json
cosmicexcuse/data/en/connectors.json
cosmicexcuse/data/en/cosmic.json
cosmicexcuse/data/en/intensifiers.json
cosmicexcuse/data/en/quantum.json
cosmicexcuse/data/en/recommendations.json
cosmicexcuse/data/en/technical.json
cosmicexcuse-0.0.2.dist-info/licenses/LICENSE
cosmicexcuse-0.0.2.dist-info/METADATA
cosmicexcuse-0.0.2.dist-info/WHEEL
cosmicexcuse-0.0.2.dist-info/entry_points.txt
cosmicexcuse-0.0.2.dist-info/top_level.txt
cosmicexcuse-0.0.2.dist-info/RECORD
