Metadata-Version: 2.4
Name: cosmicexcuse
Version: 0.0.2
Summary: Generate quantum-grade excuses for your code failures using fake AI
Home-page: https://github.com/shamspias/cosmicexcuse
Author: Shamsuddin Ahmed
Author-email: Shamsuddin Ahmed <info@shamspias.com>
License: MIT
Project-URL: Homepage, https://github.com/shamspias/cosmicexcuse
Project-URL: Bug Tracker, https://github.com/shamspias/cosmicexcuse/issues
Project-URL: Documentation, https://cosmicexcuse.readthedocs.io/
Keywords: excuse,generator,quantum,ai,humor
Classifier: Development Status :: 4 - Beta
Classifier: Intended Audience :: Developers
Classifier: Topic :: Software Development :: Libraries :: Python Modules
Classifier: License :: OSI Approved :: MIT License
Classifier: Programming Language :: Python :: 3
Classifier: Programming Language :: Python :: 3.9
Classifier: Programming Language :: Python :: 3.10
Classifier: Programming Language :: Python :: 3.11
Classifier: Programming Language :: Python :: 3.12
Requires-Python: >=3.9
License-File: LICENSE
Provides-Extra: dev
Requires-Dist: pytest>=8.4.1; extra == "dev"
Requires-Dist: pytest-cov>=6.2.1; extra == "dev"
Requires-Dist: black>=22.1.0; extra == "dev"
Requires-Dist: flake8>=7.1.1; extra == "dev"
Requires-Dist: mypy>=1.17.1; extra == "dev"
Provides-Extra: docs
Requires-Dist: sphinx>=8.1.3; extra == "docs"
Requires-Dist: sphinx-rtd-theme>=3.0.2; extra == "docs"
Dynamic: author
Dynamic: home-page
Dynamic: license-file
Dynamic: requires-python
